lightningrod/__init__.py
lightningrod/_display.py
lightningrod/_errors.py
lightningrod/client.py
lightningrod/py.typed
lightningrod/_generated/__init__.py
lightningrod/_generated/client.py
lightningrod/_generated/errors.py
lightningrod/_generated/py.typed
lightningrod/_generated/types.py
lightningrod/_generated/api/__init__.py
lightningrod/_generated/api/datasets/__init__.py
lightningrod/_generated/api/datasets/create_dataset_datasets_post.py
lightningrod/_generated/api/datasets/get_dataset_datasets_dataset_id_get.py
lightningrod/_generated/api/datasets/get_dataset_samples_datasets_dataset_id_samples_get.py
lightningrod/_generated/api/datasets/upload_samples_datasets_dataset_id_samples_post.py
lightningrod/_generated/api/file_sets/__init__.py
lightningrod/_generated/api/file_sets/add_file_to_set_filesets_file_set_id_files_post.py
lightningrod/_generated/api/file_sets/create_file_set_filesets_post.py
lightningrod/_generated/api/file_sets/get_file_set_filesets_file_set_id_get.py
lightningrod/_generated/api/file_sets/list_file_sets_filesets_get.py
lightningrod/_generated/api/file_sets/list_files_in_set_filesets_file_set_id_files_get.py
lightningrod/_generated/api/files/__init__.py
lightningrod/_generated/api/files/create_file_upload_files_post.py
lightningrod/_generated/api/open_ai_compatible/__init__.py
lightningrod/_generated/api/open_ai_compatible/chat_completions_openai_chat_completions_post.py
lightningrod/_generated/api/organizations/__init__.py
lightningrod/_generated/api/organizations/get_balance_organizations_balance_get.py
lightningrod/_generated/api/samples/__init__.py
lightningrod/_generated/api/samples/validate_sample_samples_validate_post.py
lightningrod/_generated/api/transform_jobs/__init__.py
lightningrod/_generated/api/transform_jobs/cost_estimation_transform_jobs_cost_estimation_post.py
lightningrod/_generated/api/transform_jobs/create_transform_job_transform_jobs_post.py
lightningrod_ai-0.1.6.dist-info/licenses/LICENSE
lightningrod_ai-0.1.6.dist-info/METADATA
lightningrod_ai-0.1.6.dist-info/WHEEL
lightningrod_ai-0.1.6.dist-info/top_level.txt
lightningrod_ai-0.1.6.dist-info/RECORD
