Metadata-Version: 2.4
Name: lightningrod-ai
Version: 0.1.6
Summary: Python SDK for Lightning Rod AI-powered forecasting dataset generation
Author-email: Lightning Rod Labs <support@lightningrod.ai>
License: MIT License
Project-URL: Homepage, https://lightningrod.ai/sdk
Project-URL: Repository, https://github.com/lightning-rod-labs/lightningrod-python-sdk
Requires-Python: >=3.10
License-File: LICENSE
Requires-Dist: requests>=2.31.0
Requires-Dist: pydantic>=2.0.0
Requires-Dist: httpx>=0.25.0
Requires-Dist: attrs>=23.1.0
Requires-Dist: python-dateutil>=2.8.0
Requires-Dist: pyarrow>=14.0.0
Requires-Dist: fsspec>=2023.0.0
Requires-Dist: rich>=13.0.0
Provides-Extra: dev
Requires-Dist: openapi-python-client>=0.15.0; extra == "dev"
Dynamic: license-file
